LICENSE
MANIFEST.in
README.rst
setup.py
jubakit/__init__.py
jubakit/_process.py
jubakit/_stdio.py
jubakit/_version.py
jubakit/anomaly.py
jubakit/bandit.py
jubakit/base.py
jubakit/burst.py
jubakit/classifier.py
jubakit/clustering.py
jubakit/compat.py
jubakit/dumb.py
jubakit/logger.py
jubakit/model.py
jubakit/nearest_neighbor.py
jubakit/recommender.py
jubakit/regression.py
jubakit/shell.py
jubakit/weight.py
jubakit.egg-info/PKG-INFO
jubakit.egg-info/SOURCES.txt
jubakit.egg-info/dependency_links.txt
jubakit.egg-info/entry_points.txt
jubakit.egg-info/requires.txt
jubakit.egg-info/top_level.txt
jubakit/_cli/__init__.py
jubakit/_cli/args.py
jubakit/_cli/base.py
jubakit/_cli/cmd.py
jubakit/_cli/util.py
jubakit/_cli/service/__init__.py
jubakit/_cli/service/anomaly.py
jubakit/_cli/service/bandit.py
jubakit/_cli/service/burst.py
jubakit/_cli/service/classifier.py
jubakit/_cli/service/clustering.py
jubakit/_cli/service/generic.py
jubakit/_cli/service/graph.py
jubakit/_cli/service/nearest_neighbor.py
jubakit/_cli/service/recommender.py
jubakit/_cli/service/regression.py
jubakit/_cli/service/stat.py
jubakit/_cli/service/weight.py
jubakit/loader/__init__.py
jubakit/loader/array.py
jubakit/loader/chain.py
jubakit/loader/core.py
jubakit/loader/csv.py
jubakit/loader/odbc.py
jubakit/loader/postgresql.py
jubakit/loader/sparse.py
jubakit/loader/twitter.py
jubakit/test/integration/__init__.py
jubakit/test/integration/test_model.py
jubakit/test/integration/test_shell.py
jubakit/test/integration/_cli/__init__.py
jubakit/test/integration/_cli/service/__init__.py
jubakit/test/integration/_cli/service/base.py
jubakit/test/integration/_cli/service/test_anomaly.py
jubakit/test/integration/_cli/service/test_bandit.py
jubakit/test/integration/_cli/service/test_burst.py
jubakit/test/integration/_cli/service/test_classifier.py
jubakit/test/integration/_cli/service/test_clustering.py
jubakit/test/integration/_cli/service/test_generic.py
jubakit/test/integration/_cli/service/test_graph.py
jubakit/test/integration/_cli/service/test_nearest_neighbor.py
jubakit/test/integration/_cli/service/test_recommender.py
jubakit/test/integration/_cli/service/test_regression.py
